explicit_di/__init__.py
explicit_di/_impl.py
explicit_di/py.typed
explicit_di-0.2.0.dist-info/LICENSE
explicit_di-0.2.0.dist-info/METADATA
explicit_di-0.2.0.dist-info/WHEEL
explicit_di-0.2.0.dist-info/RECORD
