Metadata-Version: 2.3
Name: explicit-di
Version: 0.2.0
Summary: 
Keywords: dependency-injection,di,dependency-injection-container
Author: Martin Vielsmaier
Author-email: martin@vielsmaier.net
Requires-Python: >=3.9,<4.0
Classifier: Development Status :: 3 - Alpha
Classifier: Intended Audience :: Developers
Classifier: License :: OSI Approved :: MIT License
Classifier: Programming Language :: Python :: 3
Classifier: Programming Language :: Python :: 3.9
Classifier: Programming Language :: Python :: 3.10
Classifier: Programming Language :: Python :: 3.11
Classifier: Programming Language :: Python :: 3.12
Classifier: Programming Language :: Python :: 3.13
Classifier: Topic :: Software Development :: Libraries
Project-URL: Changelog, https://depeche-py.github.io/explicit-di/CHANGELOG/
Project-URL: Documentation, https://depeche-py.github.io/explicit-di/
Project-URL: Homepage, https://github.com/depeche-py/explicit-di
Project-URL: Repository, https://github.com/depeche-py/explicit-di
